prana_rc/__init__.py
prana_rc/__version__.py
prana_rc/entity.py
prana_rc/utils.py
prana_rc/contrib/__init__.py
prana_rc/contrib/api/__init__.py
prana_rc/contrib/api/dto.py
prana_rc/contrib/api/handler.py
prana_rc/contrib/client/__init__.py
prana_rc/contrib/client/aiohttp.py
prana_rc/contrib/client/common.py
prana_rc.client-0.4.4.dist-info/METADATA
prana_rc.client-0.4.4.dist-info/WHEEL
prana_rc.client-0.4.4.dist-info/top_level.txt
prana_rc.client-0.4.4.dist-info/RECORD
