Metadata-Version: 2.1
Name: prana-rc.client
Version: 0.4.4
Summary: Python library and CLI to control Prana recuperators via BLE connection (https://prana.org.ua/)
Home-page: https://github.com/corvis/prana_rc
Author: Dmitry Berezovsky
License: GPLv3
Keywords: python prana recuperators iot automation
Platform: UNKNOWN
Classifier: Development Status :: 3 - Alpha
Classifier: Intended Audience :: Developers
Classifier: Topic :: Software Development :: Libraries :: Python Modules
Classifier: Topic :: Home Automation
Classifier: License :: OSI Approved :: GNU General Public License v3 (GPLv3)
Classifier: Programming Language :: Python :: 3
Classifier: Programming Language :: Python :: 3.6
Classifier: Programming Language :: Python :: 3.7
Classifier: Programming Language :: Python :: 3.8
Requires-Python: >3.6
Requires-Dist: ws-sizzle[aiohttp] (>=0.0.8)
